[
{
		"cat": "ق/00001",
		"ISBN": "9957463012",
		"titre": "معجم مصطلحات التربية و التعليم",
		"autor": "حمدان محمد",
		"edition": "عمان : كنوز المعرفة"
	},
	{
		"cat": "ق/00002",
		"ISBN": "9789963634912",
		"titre": "المورد الثلاثي للطلاب : قاموس أساسي مبسط (عربي،إنكليزي،فرنسي)",
		"autor": "البعلبكي روحي",
		"edition": "لبنان : دار العلم للملايين"
	},
	{
		"cat": "ق/00003",
		"ISBN": "9789953633749",
		"titre": "المورد الميسر : قاموس عربي،إنكليزي مبسط",
		"autor": "البعلبكي روحي",
		"edition": "بيروت : دار العلم للملايين"
	},
	{
		"cat": "ق/00004",
		"ISBN": "9957478893",
		"titre": "الموسوعة الجغرافية",
		"autor": "موسى محمود محمد",
		"edition": "عمان : دار دجلة"
	},
	{
		"cat": "ق/00005",
		"ISBN": "9789957244019",
		"titre": "قاموس مختصرات علوم المكتبات و المعلومات في بيئة الإنترنت : إنجليزي،عربي",
		"autor": "خالد توهان الزبيدي ماجد",
		"edition": "عمان : دار صفاء"
	},
	{
		"cat": "ق/00006",
		"ISBN": "995771001",
		"titre": "موسوعة بنك المعلومات",
		"autor": "أحمد الدباس ريا",
		"edition": "عمان : دار دجلة"
	},
	{
		"cat": "ق/00007",
		"ISBN": "9957710125",
		"titre": "موسوعة كنوز العلم و المعرفة",
		"autor": "محمد موسى ميداء",
		"edition": "عمان : دار دجلة"
	},
	{
		"cat": "ق/00008",
		"ISBN": "",
		"titre": "موسوعة الحضارة العربية : الحضارة الاندلسي",
		"autor": "البستاني بطرس",
		"edition": "بيروت : المركز الثقافي الحديث"
	},
	{
		"cat": "ق/00009",
		"ISBN": "9782035840783",
		"titre": "le petit larousse",
		"autor": "",
		"edition": "france : edition anniversaire de la semeuse"
	},
	{
		"cat": "ق/00010",
		"ISBN": "9957076736",
		"titre": "معجم مصطلحات التربية الخاصة و الخدمات المساندة : إنجليزي،عربي",
		"autor": "الخطيب جمال محمد",
		"edition": "عمان : دار الفكر"
	},
	{
		"cat": "ق/00011",
		"ISBN": "9789957065768",
		"titre": "المعجم الموسوعي لتكنولوجيا المعلومات و الإنترنت",
		"autor": "قنديلجي عامر إبراهيم",
		"edition": "عمان : دار المسيرة"
	},
	{
		"cat": "ق/00012",
		"ISBN": "9789957740283",
		"titre": "الكافي : في مفاهيم علوم المكتبات و المعلومات-عربي،إنجليزي-",
		"autor": "الصرايره خالد عبده",
		"edition": "عمان : كنوز المعرفة"
	},
	{
		"cat": "ق/00013",
		"ISBN": "",
		"titre": "المعجم الإعلامي",
		"autor": "الفار محمد جمال",
		"edition": "عمان : دار أسامة"
	},
	{
		"cat": "ق/00014",
		"ISBN": "",
		"titre": "المعجم الفلسفي",
		"autor": "حسيبة مصطفى",
		"edition": "عمان : دار أسامة"
	},
	{
		"cat": "ق/00015",
		"ISBN": "9775862299",
		"titre": "الموسوعة التعليمية للمصارعة الرومانية",
		"autor": "الروبي محمد رضا حافظ",
		"edition": "الإسكندرية : ماهي"
	},
	{
		"cat": "ق/00016",
		"ISBN": "",
		"titre": "موسوعة دليل تدريس التربية الرياضية في المدارس و الطب الرياضي",
		"autor": "الخالدي احمد ارشيد",
		"edition": "عمان : المعتز"
	},
	{
		"cat": "ق/00017",
		"ISBN": "9775862531",
		"titre": "دليلك إلى طرق الاختبار بكرة القدم",
		"autor": "رحمة إبراهيم",
		"edition": "الإسكندرية : ماهي"
	},
	{
		"cat": "ق/00018",
		"ISBN": "9789957064327",
		"titre": "موسوعة الغذاء و التغذية الصحية",
		"autor": "مزاهرة ايمن سليمان",
		"edition": "عمان : دار المسيرة"
	},
	{
		"cat": "ق/00019",
		"ISBN": "9770395935",
		"titre": "موسوعة محددات التدريب الرياضي النظرية و التطبيقية لتخطيط البرامج التدريبية برياضة الكاراتيه",
		"autor": "أحمد محمود محمد ابراهيم",
		"edition": "الإسكندرية : منشاة المعارف"
	},
	{
		"cat": "ق/00020",
		"ISBN": "",
		"titre": "موسوعة الإصابات الرياضية و كيفية التعامل معها",
		"autor": "فريق كمونة",
		"edition": "عمان : دار الثقافة"
	},
	{
		"cat": "ق/00021",
		"ISBN": "9772942720",
		"titre": "موسوعة الإصابات الرياضية و إسعافاتها الأولية",
		"autor": "عبد الرحمن عبد الحميد زاهر",
		"edition": "القاهرة : مركز الكتاب للنشر"
	},
	{
		"cat": "ق/00022",
		"ISBN": "9771013602",
		"titre": "موسوعة التنظيم و الإدارة في التربية البدنية و الرياضية",
		"autor": "عصام بدوي",
		"edition": "القاهرة : دار الفكر العربي"
	},
	{
		"cat": "ق/00023",
		"ISBN": "9772375515",
		"titre": "الموسوعة العلمية لاقتصاديات الرياضة : دراسات الجدوى و المشروعات الصغيرة في التربية البدنية و الرياضية",
		"autor": "حسن أحمد الشافعي",
		"edition": "الإسكندرية : دار الوفاء"
	},
	{
		"cat": "ق/00024",
		"ISBN": "9770314072",
		"titre": "موسوعة الأسس العلمية والتطبيقية لتخطيط البرامج التدريبية للجملة الحركية-الكاتا-برياضة الكاراتيه",
		"autor": "أحمد محمود محمد ابراهيم",
		"edition": "الإسكندرية : منشاة المعارف"
	},
	{
		"cat": "ق/00025",
		"ISBN": "",
		"titre": "الموسوعة التربوية للطفل كتاب 1-2-3-4.",
		"autor": "عبد الباري محمد داود",
		"edition": "الإسكندرية : مكتبة الإشعاع "
	},
	{
		"cat": "ق/00026",
		"ISBN": "9773141659",
		"titre": "معجم الإعاقة السمعية : إنجليزي-عربي/عربي -إنجليزي",
		"autor": "عبد الرحمن سيد سليمان",
		"edition": "مصر : دار القاهرة"
	},
	{
		"cat": "ق/00027",
		"ISBN": "",
		"titre": "معجم العلاج النفسي الدوائي",
		"autor": "محمد أحمد النابلسي",
		"edition": "بيروت : دار الهلال"
	},
	{
		"cat": "ق/00028",
		"ISBN": "",
		"titre": "قاموس مصطلحات علم النفس الحديث و التربية",
		"autor": "عبد الرحمن العيسوي",
		"edition": "د م ن : د د ن"
	},
	{
		"cat": "ق/00029",
		"ISBN": "",
		"titre": "موسوعة العلوم الاجتماعية",
		"autor": "ميشيل مان",
		"edition": "الإسكندرية : دار المعرفة الجامعية"
	},
	{
		"cat": "ق/00030",
		"ISBN": "",
		"titre": "موسوعة أحداث العالم : اكتشافات واختراعات-تواريخ وأحداث-إقتصاد وأعمال-معاهدات واتفاقات-مجالس وأحلاف-حروب",
		"autor": "سليم الياس",
		"edition": "بيروت : المركز الثقافي البناني"
	},
	{
		"cat": "ق/00031",
		"ISBN": "9773580245",
		"titre": "المعجم الإعلامي",
		"autor": "محمد منير حجاب",
		"edition": " القاهرة : دار الفجر"
	},
	{
		"cat": "ق/00032",
		"ISBN": "9774380347",
		"titre": "موسوعة التاريخ الإسلامي-كتاب من 1-2-3-4-5",
		"autor": "عبد اللطيف عبد الهادي السيد",
		"edition": "الإسكندرية : المكتب الجامعي الحديث"
	},
	{
		"cat": "ق/00033",
		"ISBN": "",
		"titre": "موسوعة أعلام الفلسفة العرب و الأجانب -ج1/ج2.",
		"autor": "روني إيلي ألفا",
		"edition": "بيروت : دار الكتب العلمية"
	},
	{
		"cat": "ق/00034",
		"ISBN": "9773580172",
		"titre": "الموسوعة الإعلامية-المجلد الأول-الثاني-الثالث-الرابع-الخامس-السادس-السابع",
		"autor": "محمد منير حجاب",
		"edition": "القاهرة : دار الفجر"
	},
	{
		"cat": "ق/00035",
		"ISBN": "9772812096",
		"titre": "موسوعة من عيون الكتب في الاجتماع",
		"autor": "نعمات أحمد فؤاد",
		"edition": "القاهرة : المكتبة الأكاديمية "
	},
	{
		"cat": "ق/00036",
		"ISBN": "9775723825",
		"titre": "الموسوعة الثقافية للوعي البيئي",
		"autor": "مصطفى كمال محمد",
		"edition": "القاهرة : إيتراك"
	},
	{
		"cat": "ق/00037",
		"ISBN": "996110191",
		"titre": "قاموس مصطلحات علم الإجتماع",
		"autor": "فاروق مداس",
		"edition": "الجزائر : دار مدني"
	},
	{
		"cat": "ق/00038",
		"ISBN": "996152098",
		"titre": "معجم مصطلحات علم النفس",
		"autor": "جابري لمياء ",
		"edition": "الجزائر : دار الخلدونية"
	},
	{
		"cat": "ق/00039",
		"ISBN": "",
		"titre": "معجم مصطلحات علم النفس الصناعي و التنظيمي و الإدارة : إنجليزي-عربي",
		"autor": "عمار الطيب كشرود",
		"edition": "ليبيا : جامعة قار يونس"
	},
	{
		"cat": "ق/00040",
		"ISBN": "9957478095",
		"titre": "معجم التصحيحات اللغوية المعاصرة",
		"autor": "غازي جاسم العنبكي",
		"edition": "عمان : دار دجلة"
	},
	{
		"cat": "ق/00041",
		"ISBN": "",
		"titre": "الموسوعة العلمية لاقتصاديات الرياضة : الاستثمار و التسويق في التربية البدنية و الرياضية",
		"autor": "حسن أحمد الشافعي",
		"edition": "الإسكندرية : الوفاء"
	},
	{
		"cat": "ق/00042",
		"ISBN": "9773274365",
		"titre": "موسوعة بيولوجيا الرياضة -1- : كيمياء الإصابة العضلية و المجهود البدني للرياضيين",
		"autor": "فراج عبد الحميد توفيق",
		"edition": "الإسكندرية : دار الوفاء"
	},
	{
		"cat": "ق/00043",
		"ISBN": "9773274357",
		"titre": "النواحي الفنية : الوثب و القفز-1- / لمسابقات الدفع و الرمي-2- / العدو و الجري و الحواجز و الموانع-3",
		"autor": "فراج عبد الحميد توفيق",
		"edition": "الإسكندرية : دار الوفاء"
	},
	{
		"cat": "ق/00044",
		"ISBN": "",
		"titre": "موسوعة كتب علم النفس الحديث : سيكولوجية المجرم - سيكولوجية العمل و العمال - العلاج السلوكي -سيكولوجية الجسم و النفس",
		"autor": "عبد الرحمن العيسوي",
		"edition": "بيروت : د.ر.ج"
	},
	{
		"cat": "ق/00045",
		"ISBN": "",
		"titre": "موسوعة الألعاب الصغيرة ",
		"autor": "مصطفى السايح محمد",
		"edition": "الإسكندرية : الوفاء"
	},
	{
		"cat": "ق/00046",
		"ISBN": "",
		"titre": "موسوعة حماية البئية-ج1/ج2.",
		"autor": "محمود صالح العادلي",
		"edition": "الإسكندرية : دار الفكر الجامعي"
	},
	{
		"cat": "ق/00047",
		"ISBN": "",
		"titre": "موسوعة علماء التربية و علماء النفس",
		"autor": "موريس شربل",
		"edition": "بيروت : دار الكتب العلمية"
	},
	{
		"cat": "ق/00048",
		"ISBN": "",
		"titre": "قاموس علم الاجتماع",
		"autor": "محمد عاطف غيث",
		"edition": "الإسكندرية : دار المعرفة الجامعية"
	},
	{
		"cat": "ق/00049",
		"ISBN": "284305493",
		"titre": "دليل المصطلحات التنموية ",
		"autor": "مجيد مسعود",
		"edition": "سوريا : المدى"
	},
	{
		"cat": "ق/00050",
		"ISBN": "9773273288",
		"titre": "الموسوعة العلمية للإدارة الرياضية : الإمكانات و المنشآت في المجال الرياضي",
		"autor": "ابراهيم محمود عبد المقصود",
		"edition": "الإسكندرية : الوفاء"
	},
	{
		"cat": "ق/00051",
		"ISBN": "9773276740",
		"titre": "الموسوعة العلمية للإدارة الرياضية : الحوكمة في التربية البدنية و الرياضية",
		"autor": "حسن أحمد الشافعي",
		"edition": "الإسكندرية : الوفاء"
	},
	{
		"cat": "ق/00052",
		"ISBN": "",
		"titre": "المعجم التربوي و علم النفس",
		"autor": "نايف القيسي",
		"edition": "عمان : دار أسامة"
	},
	{
		"cat": "ق/00053",
		"ISBN": "9947262368",
		"titre": "موسوعة علم الإجتماع و مفاهيم في السياسة و الاقتصاد و الثقافة العامة",
		"autor": "عبد المجيد لبصير",
		"edition": "عين مليلة : دار الهدى"
	},
	{
		"cat": "ق/00054",
		"ISBN": "",
		"titre": "موسوعة تاريخ اوروبا الحديث و المعاصر(ج1-ج2-ج3-ج4)",
		"autor": "مفيد الزيدي",
		"edition": "عمان : دار أسامة"
	},
	{
		"cat": "ق/00055",
		"ISBN": "9947833940",
		"titre": "المعجم الموسوعي لمصطلحات الثورة الجزائرية 1954-1962",
		"autor": "عبد الملك مرتاض",
		"edition": "الجزائر : دار الكتاب العربي"
	},
	{
		"cat": "ق/00056",
		"ISBN": "9771009966",
		"titre": "دليل الشباب المصور للألعاب الأوليمبية",
		"autor": "أمين أنور الخولي",
		"edition": "القاهرة : دار الفكر العربي"
	},
	{
		"cat": "ق/00057",
		"ISBN": "9990610835",
		"titre": "معجم علوم المكتبات و المعلومات : إنجليزي-عربي مع كشاف عربي -إنجليزي",
		"autor": "ياسر يوسف عبد المعطي",
		"edition": "الكويت : مجلس النشر العلمي"
	},
	{
		"cat": "ق/00058",
		"ISBN": "",
		"titre": "موسوعة تاريخ المغرب العربي : المجلد 1(ج1-ج2)-المجلد2(ج3-ج4)-المجلد 3(ج5-ج6)",
		"autor": "عبد الفتاح مقلد الغنيمي",
		"edition": "القاهرة : مكتبة مدبولي"
	},
	{
		"cat": "ق/00059",
		"ISBN": "9789953505077",
		"titre": "بنك الثقافة الموسوعة الأشمل في المعلومات",
		"autor": "طلال عزيز ",
		"edition": "لبنان : كتابنا"
	},
	{
		"cat": "ق/00060",
		"ISBN": "",
		"titre": "بنك المعلومات 2009 : المجلد الأول 1-5",
		"autor": "محمود برهوم",
		"edition": "الأردن : الفكر"
	},
	{
		"cat": "ق/00061",
		"ISBN": "",
		"titre": "كشاف موسوعة الثقافة التاريخية والأثرية والحضارية",
		"autor": "فهيم مصطفى",
		"edition": "القاهرة : الفكر العربي"
	},
	{
		"cat": "ق/00062",
		"ISBN": "9789953505466",
		"titre": "موسوعة أشهر النساء في التاريخ الوسيط و المعاصر",
		"autor": "عبد الحميد ديوان",
		"edition": "لبنان : دار كتابنا"
	},
	{
		"cat": "ق/00063",
		"ISBN": "",
		"titre": "موسوعة تاريخ الإمبراطورية العثمانية السياسي و العسكري و الحضاري : مجلد1/2/3/4.",
		"autor": "يلماز أوزتونا",
		"edition": "بيروت : الدار العربية للموسوعات"
	},
	{
		"cat": "ق/00064",
		"ISBN": "9773143317",
		"titre": "موسوعة الصحة النفسية (جزء1و2) : علم الأمراض النفسية و العقلية (الأسباب، الأعراض، التشخيص، العلاج)",
		"autor": "محمد السيد عبد الرحمن",
		"edition": "القاهرة : مكتبة زهراء الشرق"
	},
	{
		"cat": "ق/00065",
		"ISBN": "9789953723181",
		"titre": "القاموس المحيط ",
		"autor": "مجد الدين محمد بن يعقوب الفيروز آبادي",
		"edition": "بيروت : دار الأرقم"
	},
	{
		"cat": "ق/00066",
		"ISBN": "9789953890388",
		"titre": "المنهل : قاموس فرنسي-عربي",
		"autor": "سهيل إدريس",
		"edition": "بيروت : دار الآداب"
	},
	{
		"cat": "ق/00067",
		"ISBN": "9789957245931",
		"titre": "قاموس لغة الإشارة للصم",
		"autor": "ماجدة السيد عبيد",
		"edition": "عمان : دار الصفاء"
	},
	{
		"cat": "ق/00068",
		"ISBN": "2745152041",
		"titre": "معجم الطلاب الوسيط عربي - عربي",
		"autor": "كريم سيد محمد محمود",
		"edition": "بيروت : دار الكتب العلمية"
	},
	{
		"cat": "ق/00069",
		"ISBN": "",
		"titre": "موسوعة الخدمة الاجتماعية المعاصرة",
		"autor": "صالح الصقور",
		"edition": "عمان : دار زهران"
	},
	{
		"cat": "ق/00070",
		"ISBN": "9789957067977",
		"titre": "موسوعة المصطلحات التربوية",
		"autor": "محمد السيد علي",
		"edition": "عمان : دار المسيرة"
	},
	{
		"cat": "ق/00071",
		"ISBN": "9957710583",
		"titre": "معجم المصطلحات البيئية ",
		"autor": "سحر أمين كاتوت",
		"edition": "عمان : دار دجلة"
	},
	{
		"cat": "ق/00072",
		"ISBN": "9772942631",
		"titre": " الكونغ - فو ج1- ج2- ج3 : الساندا و الأساليب الدولية / أعنف الرياضات في العالم مع الساندا و الأساليب الدولية / اللياقة البدنية",
		"autor": "أحمد إبراهيم أبو بكر",
		"edition": "القاهرة : مركز الكتاب للنشر"
	},
	{
		"cat": "ق/00073",
		"ISBN": "9789961014578",
		"titre": "دليل مصطلحات علم اجتماع التنظيم والعمل",
		"autor": "ناصر قاسمي",
		"edition": "الجزائر : د م ج"
	},
	{
		"cat": "ق/00074",
		"ISBN": "9789961809037",
		"titre": "المغيث : معجم قانون تكنولوجيات الإعلام والإتصال عربي فرنسي إنجليزي",
		"autor": "دحمان مجيد",
		"edition": "2008"
	},
	{
		"cat": "ق/00075",
		"ISBN": "",
		"titre": "موسوعة الاديان في العالم : الدروز و الموحدون",
		"autor": "دار كريبس أنترناشيونال",
		"edition": "دار كريبس أنترناشيونال : دار كريبس أنترناشيونال"
	},
	{
		"cat": "ق/00076",
		"ISBN": "9953753652",
		"titre": "قاموس المصطلحات الإعلامية : إنكليزي- عربي .",
		"autor": "عزت محمدفريد محمود",
		"edition": "بيروت : الهلال"
	},
	{
		"cat": "ق/00077",
		"ISBN": "9772942305",
		"titre": "موسوعة فسيولوجيا مسابقات الرمى : 1000 تدريب للكفاءة الفيسيولوجية والحركية والمهارية",
		"autor": "زاهر عبد الرحمان عبد الحميد",
		"edition": "القاهرة : مركز الكتاب"
	},
	{
		"cat": "ق/00078",
		"ISBN": "",
		"titre": "موسوعة علم النفس : المجلد الأول - المجلد الثاني - المجلد الثالث ",
		"autor": "رولان دورون و آخرون",
		"edition": "لبنان : منشورات عويدات"
	},
	{
		"cat": "ق/00079",
		"ISBN": "1110325",
		"titre": "معجم العمارة و الفن : عربي فرنسي - فرنسي عربي-مع مسرد فرنسي إنجليزي",
		"autor": "البهنسي عفيف ",
		"edition": "لبنان : مكتبة لبنان ناشرون "
	},
	{
		"cat": "ق/00080",
		"ISBN": "",
		"titre": "الموسوعة العامة لتاريح المغرب و الاندلس الجزء الاول-الجزءالثالث - الجزء الرابع - الجزء الخامس",
		"autor": "زبيب نجيب",
		"edition": "لبنان : دار الامير للثقافة و العلوم"
	},
	{
		"cat": "ق/00081",
		"ISBN": "",
		"titre": "موسوعة لالاند الفلسفية المجلد الأول",
		"autor": "لالاندأندريه",
		"edition": "بيروت : منشورات عويدات "
	},
	{
		"cat": "ق/00082",
		"ISBN": "9773081648",
		"titre": "مصادر التربية الاسلامية- معجم الادباء- : لياقوت الحموي نمودجا",
		"autor": "عيسى موهوب محمد",
		"edition": "الاسكندرية : العلم والايمان"
	},
	{
		"cat": "ق/00083",
		"ISBN": "9957221833",
		"titre": "معجم الطب النفسي و العقلي ",
		"autor": "محمود عواد",
		"edition": "عمان : أسامة "
	},
	{
		"cat": "ق/00084",
		"ISBN": "9789957710200",
		"titre": "موسوعة الظواهر الخارقة ",
		"autor": "نور صاحب شنوت ",
		"edition": "عمان : دجلة "
	},
	{
		"cat": "ق/00085",
		"ISBN": "9789957123932",
		"titre": "موسوعة ألعاب القوى العالمية ",
		"autor": "شبيب نعمان السعدون",
		"edition": "عمان : اليازوري"
	},
	{
		"cat": "ق/00086",
		"ISBN": "9789957710132",
		"titre": "الموسوعة الطبيعية",
		"autor": "عامر عبد الفتاح الكيلاني ",
		"edition": "عمان : دجلة"
	},
	{
		"cat": "ق/00087",
		"ISBN": "9789957710194",
		"titre": "موسوعة الأساطير و القصص ",
		"autor": "نور صاحب شنوت ",
		"edition": "عمان : دجلة "
	},
	{
		"cat": "ق/00088",
		"ISBN": "",
		"titre": "موسوعة الصحة الجنسية : للرجل و المرأة ",
		"autor": "مصطفى فتحي ",
		"edition": "عمان : أسامة "
	},
	{
		"cat": "ق/00089",
		"ISBN": "",
		"titre": "موسوعة الألعاب الرياضية",
		"autor": "محمد كرار",
		"edition": "عمان : دار أسامة"
	},
	{
		"cat": "ق/00090",
		"ISBN": "",
		"titre": "موسوعة الألعاب المسلية",
		"autor": "منى الطائي",
		"edition": "عمان : أسامة"
	},
	{
		"cat": "ق/00091",
		"ISBN": "",
		"titre": "الوجيز في الطب الشرعي",
		"autor": "آمال عبد الرزاق مشالي",
		"edition": "الإسكندرية : مكتبة الوفاء"
	},
	{
		"cat": "ق/00092",
		"ISBN": "9789953537511",
		"titre": "معجم الطب النفسي والانجرافات كما العلاجات النفسية الحضارية ",
		"autor": "علي زيعور",
		"edition": "لبنان : النهضة العربية"
	},
	{
		"cat": "ق/00093",
		"ISBN": "",
		"titre": "موسوعة الآثار التاريخية",
		"autor": "حسين فهد حماد",
		"edition": "الأردن : أسامة"
	},
	{
		"cat": "ق/00094",
		"ISBN": "",
		"titre": "دليل المترجم الصحفي والإعلامي : الترجمة الصحفية والمصطلحات الإعلامية ج 1-ج 2",
		"autor": "ماجد سليمان دودين",
		"edition": "الأردن : مكتبة المجتمع العربي"
	},
	{
		"cat": "ق/00095",
		"ISBN": "9789957478698",
		"titre": "موسوعة الألعاب الرياضية ",
		"autor": "خلود مانع الزبيدي",
		"edition": "الأردن : دجلة"
	},
	{
		"cat": "ق/00096",
		"ISBN": "",
		"titre": "تطوير المهارات اللغوية بالانجليزية : الإستماع والتحدث والقراءة والكتابة",
		"autor": " ماجد سليمان دودين",
		"edition": "الأردن : مكتبة المجتمع العربي"
	},
	{
		"cat": "ق/00097",
		"ISBN": "9789961652398",
		"titre": "معجم مصطلحات علم النفس : عربي/فرنسي",
		"autor": "عبد الرحمن الوافي",
		"edition": "الجزائر : هومة"
	},
	{
		"cat": "ق/00098",
		"ISBN": "",
		"titre": "المعجم الجغرافي",
		"autor": "أمنة أبو حجر",
		"edition": "الأردن : أسامة"
	},
	{
		"cat": "ق/00099",
		"ISBN": "9772156520",
		"titre": "الموسوعة العربية للعلوم التنموية ك1 علم الإجتماع البدوي : التأصيل النظري ",
		"autor": "الفوال صلاح مصطفى ",
		"edition": "القاهرة : دار غريب "
	},
	{
		"cat": "ق/00100",
		"ISBN": "",
		"titre": "الموسوعة العلمية الإقتصادية الرياضية التربس-الويبو-الفرنشايز في التربية البدنية والرياضية",
		"autor": "حسن أحمد الشافعي",
		"edition": "الإسكندرية : الوفاء"
	},
	{
		"cat": "ق/00101",
		"ISBN": "9775862620",
		"titre": "الإعلام والعلاقات العامة في المجال الرياضي",
		"autor": "سمير عبد الحميد علي",
		"edition": "الاسكندرية : ماهي"
	},
	{
		"cat": "ق/00102",
		"ISBN": "",
		"titre": "موسوعة الطفل الصحية والنفسية : مراحل نمو الطفل المثالي - التربية الصحية للطفل - الخوف و القلق عند الأطفال - التربية النفسية للطف",
		"autor": "عكاشة عبد المنان الطيبي",
		"edition": "بيروت : الجيل"
	},
	{
		"cat": "ق/00103",
		"ISBN": "9775020042",
		"titre": "قاموس علم الاجتماع",
		"autor": "عبد الهادي الجوهري",
		"edition": "الاسكندرية : المكتب الجامعي الحديث"
	},
	{
		"cat": "ق/00104",
		"ISBN": "",
		"titre": "الموسوعة العليمية التعليمية: مبادئ رياضة الجودو",
		"autor": "محمد رضا حافظ الروبي و آخرون",
		"edition": "الاسكندرية : ماهي لخدمات الكمبيوتر"
	},
	{
		"cat": "ق/00105",
		"ISBN": "",
		"titre": "الموسوعة العلمية التعليمية:2.3.3.2 أفضل خطة لعب في عالم كرة القدم",
		"autor": "زهران عبد الله",
		"edition": "الاسكندرية : ماهر لخدمات الكمبيوتر"
	},
	{
		"cat": "ق/00106",
		"ISBN": "9773143236",
		"titre": "معجم مصطلحات الاضطرابات السلوكية والانفعالية",
		"autor": "عبد الرحمن سيد سليمان",
		"edition": "القاهرة : مكتبة زهراء الشرق"
	},
	{
		"cat": "ق/00107",
		"ISBN": "9789957478636",
		"titre": "موسوعة الإسعافات الأولية ",
		"autor": "فرح الزبيدي",
		"edition": "الأردن : دجلة "
	},
	{
		"cat": "ق/00108",
		"ISBN": "",
		"titre": "موسوعة الطب النفسي",
		"autor": "عبد الكريم الحجاوي",
		"edition": "الأردن : أسامة "
	},
	{
		"cat": "ق/00109",
		"ISBN": "9953484740",
		"titre": "هم أحق بالرعاية ( الطفل المعاق ) : موسوعة سيكولوجيا الطفل",
		"autor": "ريان سليم بدير ",
		"edition": "لبنان : الهادي "
	},
	{
		"cat": "ق/00110",
		"ISBN": "9953484767",
		"titre": "علم النفس في التربية الفنية : موسوعة سيكولوجيا الطفل",
		"autor": "ريان سليم بدير ",
		"edition": "لبنان : الهادي"
	},
	{
		"cat": "ق/00111",
		"ISBN": "9953484775",
		"titre": "الصحة النفسية للطفل : موسوعة سيكولوجيا الطفل",
		"autor": "ريان سليم بدير",
		"edition": "لبنان : الهادي"
	},
	{
		"cat": "ق/00112",
		"ISBN": "9953484716",
		"titre": "اللعب عند الطفل : موسوعة سيكولوجيا الطفل",
		"autor": "ريان سليم بدير ",
		"edition": "لبنان : الهادي "
	},
	{
		"cat": "ق/00113",
		"ISBN": "9953484732",
		"titre": "تغذية الطفل : موسوعة سيكولوجية الطفل",
		"autor": "ريان سليم بدير",
		"edition": "لبنان : الهادي "
	},
	{
		"cat": "ق/00114",
		"ISBN": "9953484783",
		"titre": "سيكولوجية رسوم الأطفال : موسوعة سيكولوجية الطفل",
		"autor": "ريان سليم بدير ",
		"edition": "لبنان : الهادي"
	},
	{
		"cat": "ق/00115",
		"ISBN": "9953484759",
		"titre": "التربية الإسلامية للطفل : موسوعة سيكولوجيا الطفل",
		"autor": "ريان سليمبدير",
		"edition": "لبنان : الهادي"
	},
	{
		"cat": "ق/00116",
		"ISBN": "9953484724",
		"titre": "الطفل مع الإعلام والتلفزيون : موسوعة سيكولوجيا الطفل",
		"autor": "ريان سليم بدير",
		"edition": "لبنان : الهادي"
	},
	{
		"cat": "ق/00117",
		"ISBN": "9771009907",
		"titre": "موسوعة تدريب كرة السلة : برامج التدربيب البدنى والمهارى والخططى والنفسى والعقلى",
		"autor": "مصطفى زيدان",
		"edition": "القاهرة : الفكر العربي "
	},
	{
		"cat": "ق/00118",
		"ISBN": "9789957710026",
		"titre": "موسوعة التلربية النفسية للأطفال ",
		"autor": "مي محمد موسى محمود",
		"edition": "عمان : جلة"
	},
	{
		"cat": "ق/00119",
		"ISBN": "9772944022",
		"titre": "موسوعة التمرينات التطبيقية للألعاب الرياضية كافة",
		"autor": "انا إسكارود يموفا",
		"edition": "القاهرة : الكتاب للنشر"
	},
	{
		"cat": "ق/00120",
		"ISBN": "",
		"titre": "الأتجاهات الحديثة للتدريب الرياضى بالاتحادات الرياظية الفلسطينية : الموسوعة العلمية الرياظية جزء 2",
		"autor": "عمر نصر الله قشطه",
		"edition": "الإسكندرية : الوفاء"
	},
	{
		"cat": "ق/00121",
		"ISBN": "9953301425",
		"titre": "الأخصائي النفسي : موسوعة ميادين علم النفس",
		"autor": "عبد الرحمن العيسوي",
		"edition": "لبنان : الراتب الجامعية"
	},
	{
		"cat": "ق/00122",
		"ISBN": "",
		"titre": "موسوعة التربية الخاصة والتأهيل النفسي",
		"autor": "كمال سالم سيسالم",
		"edition": "العين : الكتاب الجامعي"
	},
	{
		"cat": "ق/00123",
		"ISBN": "9772940590",
		"titre": "موسوعة الاختبارات النفسية للرياضيين",
		"autor": "محمد حسن علاوي",
		"edition": "القاهرة : مركز الكتاب "
	},
	{
		"cat": "ق/00124",
		"ISBN": "",
		"titre": "التربية النفسية للطفل والمراهق : موسوعة كتب علم النفس الحديث",
		"autor": "عبد الرحمن العيسوي",
		"edition": "لبنان : الراتب الجامعية "
	},
	{
		"cat": "ق/00125",
		"ISBN": "9772940744",
		"titre": "الألعاب التكتيكية والترويحية الحديثة في كرة القدم : الموسوعة العربية لتطوير برامج التدريب للكبار والناشئين ",
		"autor": "عمرو أبو المجد",
		"edition": "القاهرة : مركز الكتاب للنشر"
	},
	{
		"cat": "ق/00126",
		"ISBN": "977388032",
		"titre": "موسوعة مصطلحات الطفولة : اجتماعية -اعلامية -تربوية-نفسية -طبية ",
		"autor": "إسماعيل عبد الفتاح عبد الكافي",
		"edition": "الاسكندرية : مركز الاسكندرية للكتاب"
	},
	{
		"cat": "ق/00127",
		"ISBN": "9957400487",
		"titre": "الموسوعة العلمية للكرة الطائرة : مهارات -خطط-اختبارات بدنية ومهارية...",
		"autor": "مروان عبد المجيد إبراهيم",
		"edition": "الأردن : مؤسسة الوراق للنشر"
	},
	{
		"cat": "ق/00128",
		"ISBN": "9789957064099",
		"titre": "مفاهيم ومصطلحات في العلوم التربوية",
		"autor": "نواف أحمد سمارة",
		"edition": "الأردن : المسيرة"
	},
	{
		"cat": "ق/00129",
		"ISBN": "",
		"titre": "موسوعة شرح المصطلحات النفسية : انجليزي-فرنسي",
		"autor": "لطفي الشربيني",
		"edition": "لبنان : النهضة العربية"
	},
	{
		"cat": "ق/00130",
		"ISBN": "9772708213",
		"titre": "معجم المصطلحات التربوية والنفسية : عربي-انجليزي/انجليزي-عربي",
		"autor": "حسن شحاتة",
		"edition": "القاهرة : الدار المصرية اللبنانية"
	},
	{
		"cat": "ق/00131",
		"ISBN": "9772941910",
		"titre": "موسوعة الثقافة الأولمبية",
		"autor": "كمال عبد الحميد إسماعيل",
		"edition": "القاهرة : مركز الكتاب للنشر"
	},
	{
		"cat": "ق/00132",
		"ISBN": "",
		"titre": "قاموس الطفل الطبى ",
		"autor": "محمد رفعت",
		"edition": "بيروت : مكتبة الهلال"
	},
	{
		"cat": "ق/00133",
		"ISBN": "",
		"titre": "سيكولوجية الجسم والنفس مع داسات ميدانية على عينات عربية",
		"autor": "عبد الرحمن العيسوي",
		"edition": "بيروت : الراتب الجامعية"
	},
	{
		"cat": "ق/00134",
		"ISBN": "9773030008",
		"titre": "علم النفس الإكلينيكى : موسوعة علم النفس العيادى",
		"autor": "حسن مصطفى عبد المعطى",
		"edition": "القاهرة : قباء "
	},
	{
		"cat": "ق/00135",
		"ISBN": "9775862299",
		"titre": " مبادئ التدريب في رياضة المصارعة الأداء الفني للحركات في المصارعة اليونانية - الرومانية ",
		"autor": "محمد رضا حافظ الروبى",
		"edition": "الإسكندرية : ماهي لخدمات الكمبيوتر"
	},
	{
		"cat": "ق/00136",
		"ISBN": "9773277106",
		"titre": "معجم المصطلحات الارسطية : مفهومها ودلالتها ",
		"autor": "محمد جمال الكيلاني",
		"edition": "الاسكندرية : الوفاء"
	},
	{
		"cat": "ق/00137",
		"ISBN": "9789776229228",
		"titre": "معجم مصطلحات المترجم ",
		"autor": "محمود محمد ",
		"edition": "القاهرة : د.م.ع "
	},
	{
		"cat": "ق/00138",
		"ISBN": "284409869",
		"titre": "موسوعة علم النفس القرآني: القرآن وعلم النفس الجزء الثاني - الثالث - الرابع : الإدراك الإنساني- الإدراك الإنساني (القسم الثاني) -",
		"autor": "عبد العلي الجسماني",
		"edition": "بيروت : العربية للعلوم"
	},
	{
		"cat": "ق/00139",
		"ISBN": "9961718003",
		"titre": "المصطلح مسرد عربي- فرنسي /فرنسي- عربي : علم النفس وعلم النفس المرضي الإكلينيكي",
		"autor": "محمد شلبي",
		"edition": "(د،م) : دار الجزائرية "
	},
	{
		"cat": "ق/00140",
		"ISBN": "",
		"titre": "التعليم وعملياته الأساسية : التفكير-اللغة -التوافق",
		"autor": "ليندا دافيدوف",
		"edition": "الدار الدولية : سيد الطواب"
	},
	{
		"cat": "ق/00141",
		"ISBN": "9770305928",
		"titre": "الموسوعة العلمية للإدارة الرياضية : ج1-ج2-ج3-ج4-ج5-ج6-ج7",
		"autor": "عبد المقصود ابراهيم محمود ",
		"edition": "الاسكندرية : منشأة المعارف"
	},
	{
		"cat": "ق/00142",
		"ISBN": "",
		"titre": "السلوك الاجتماعي : الوراثة-البيئة والروابط الاجتماعية ",
		"autor": "ليندا دافيدوف ",
		"edition": "القاهرة : الدار الدولية للاستثمارات "
	},
	{
		"cat": "ق/00143",
		"ISBN": "",
		"titre": "السلوك الشاذ وسبل علاجه",
		"autor": "ليندا.دافيدوف",
		"edition": "القاهرة : الدار الدولية للاستثمارات "
	},
	{
		"cat": "ق/00144",
		"ISBN": "9772820692",
		"titre": "الشخصية الدفاعية والانفعالات",
		"autor": "ليندا دافيدوف ",
		"edition": "القاهرة : الدولية للاستثمارات "
	},
	{
		"cat": "ق/00145",
		"ISBN": "",
		"titre": "الموسوعة الفلكية الحديثة ",
		"autor": "مجاهد عماد ",
		"edition": "بيروت : م.ع.د.ن "
	},
	{
		"cat": "ق/00146",
		"ISBN": "",
		"titre": "معجم مصطلحات التحليل النفسي",
		"autor": "جان لابلانش و ج. ب. بونتاليس",
		"edition": "الجزائر : ديوان المطبوعات الجامعية "
	},
	{
		"cat": "ق/00147",
		"ISBN": "",
		"titre": "موسوعة قبائل العرب - الجزء الأول -",
		"autor": "عبد الحكيم الوائلي",
		"edition": "عمان : أسامة"
	},
	{
		"cat": "ق/00148",
		"ISBN": "",
		"titre": "موسوعة التاريخ الاسلامي : عصر المملوكي-عصر العثماني-العصر العباسي- العصر الأموي- العصر النبوة-عصر الخفاء الراشدين",
		"autor": "مفيد الزيدي وأخرون",
		"edition": "عمان : أسامة"
	},
	{
		"cat": "ق/00149",
		"ISBN": "",
		"titre": "موسوعة تاريخ المملكة العربية السعودية : ",
		"autor": "مفيد الزيدي",
		"edition": "عمان : دار أسامة"
	},
	{
		"cat": "ق/00150",
		"ISBN": "",
		"titre": "معجم مصطلحات الإعلام - انجليزي - عربي -",
		"autor": "طارق سيد أحمد الخليفى",
		"edition": "الاسكندرية : المعرفة الجامعية"
	},
	{
		"cat": "ق/00151",
		"ISBN": "",
		"titre": "الموسوعة التاريخية لدول العالم وقادتها",
		"autor": "سفيان الصفدي",
		"edition": "عمان : أسامة "
	},
	{
		"cat": "ق/00152",
		"ISBN": "",
		"titre": "موسوعة الحضارات القديمة والحديثة وتاريخ الأمم - الجزء الثاني -",
		"autor": "محمود شاكر",
		"edition": "عمان : أسامة"
	},
	{
		"cat": "ق/00153",
		"ISBN": "",
		"titre": "موسوعة المدن الاسلامية",
		"autor": "امنة ابو حجر",
		"edition": "الاردن : اسامة للنشر"
	},
	{
		"cat": "ق/00154",
		"ISBN": "",
		"titre": "موسوعة اعلام وقادة الفتح الاسلامي",
		"autor": "محمود شاكر",
		"edition": "الاردن : دار اسامة"
	},
	{
		"cat": "ق/00155",
		"ISBN": "9953484864",
		"titre": "العزوبة والانحلال الخلقي : حوارية بمنظار الواقع",
		"autor": "محسن النوري الموسوي",
		"edition": "لبنان : دار الهادي"
	},
	{
		"cat": "ق/00156",
		"ISBN": "9789957478889",
		"titre": "موسوعة الوطن العربي",
		"autor": "محمد موسى محمود",
		"edition": "الأردن : دار دجلة"
	},
	{
		"cat": "ق/00157",
		"ISBN": "9789961609163",
		"titre": "جرائم الصحافة في التشريع الجزائري : موسوعة الفكر القانوني",
		"autor": "نبيل صقر",
		"edition": "الجزائر : دار الهدى"
	},
	{
		"cat": "ق/00158",
		"ISBN": "9953484848",
		"titre": "الكشكول في الزواج وقضايا الأسرة",
		"autor": "محسن التوري الموسوي",
		"edition": "لبنان : دار الهادي"
	},
	{
		"cat": "ق/00159",
		"ISBN": "",
		"titre": "معجم مصطلحات التاريخ",
		"autor": "يحي محمد نبهان",
		"edition": "الأردن : دار يافا"
	},
	{
		"cat": "ق/00160",
		"ISBN": "9773143511",
		"titre": "الآثار الإسلامية في الجزيرة العربية والمشرق والمغرب خلال العصرين النبوي والراشدي",
		"autor": "عبد الله كامل موسى",
		"edition": "القاهرة : مكتبة زهراء الشرق"
	},
	{
		"cat": "ق/00161",
		"ISBN": "977339218",
		"titre": "المفاهيم والمصطلحات البيئية ",
		"autor": "إسماعيل عبد الفتاح عبد الكافي ",
		"edition": "القاهرة : الدار الثقافية للنشر"
	},
	{
		"cat": "ق/00162",
		"ISBN": "9773562360",
		"titre": "الإعلام التربوي الإذاعة- الصحافة المدرسية",
		"autor": "محمد أبو زيد",
		"edition": "القاهرة : دار هلا"
	},
	{
		"cat": "ق/00163",
		"ISBN": "9789957331139",
		"titre": "المعجم الجامع لعلوم البيئة والموارد الطبيعية ",
		"autor": "حميد مجيد البياتي ",
		"edition": "الأردن : مؤسسة الوراق"
	},
	{
		"cat": "ق/00164",
		"ISBN": "9773502090",
		"titre": "القاموس الشارح في علوم المكتبات والمعلومات",
		"autor": "ياسر يوسف عبد المعطي",
		"edition": "القاهرة : دار الكتاب الحديث"
	},
	{
		"cat": "ق/00165",
		"ISBN": "",
		"titre": "التنبيه والإشراف ",
		"autor": "المسعودي أبو الحسن ",
		"edition": "لبنان : دار الهلال "
	},
	{
		"cat": "ق/00166",
		"ISBN": "",
		"titre": "من الفلسفة اليونانية إلى الفلسفة الإسلامية : الموسوعة الفلسفية الشاملة ",
		"autor": "محمد عبد الرحمن مرحبا",
		"edition": "لبنان : عويدات "
	},
	{
		"cat": "ق/00167",
		"ISBN": "",
		"titre": "معجم العلوم الاجتماعية : لنجايزي -فرنسي -عربي",
		"autor": "فريدريك معتوق",
		"edition": "لبنان : أكاديميا"
	},
	{
		"cat": "ق/00168",
		"ISBN": "",
		"titre": "المعجم النقدي لعلم الإجتماع",
		"autor": "بودون وف .بوريكو",
		"edition": "د م ن : د م ج"
	},
	{
		"cat": "ق/00169",
		"ISBN": "9957001078",
		"titre": "معجم علم الاجتماع المعاصر",
		"autor": "معن خليل العمر",
		"edition": "الأردن : دار الشروق"
	},
	{
		"cat": "ق/00170",
		"ISBN": "9775784913",
		"titre": "االقاموس المتخصص الفلسفة و الاجتماع : أنجليزي -فرنسي- عربي",
		"autor": "بهاء الحسيني",
		"edition": "القاهرة : هلا"
	},
	{
		"cat": "ق/00171",
		"ISBN": "9775784905",
		"titre": "القاموس المتخصص البشري : إنجليزي -فرنسي -عربي",
		"autor": "بهاء الحسيني",
		"edition": "القاهرة : عربية"
	},
	{
		"cat": "ق/00172",
		"ISBN": "9960803325",
		"titre": "الموسوعة العربية العالمية : من 1 إلى 18 من 20 إلى 30",
		"autor": "سلطان بن عبد العزيز آل سعود",
		"edition": "السعودية : مؤسسة أعمال الموسوعة"
	},
	{
		"cat": "ق/00173",
		"ISBN": "9960206645",
		"titre": "مصطلحات ومفاهيم انجليزية في الخدمة الإجتماعية ",
		"autor": "عبد المجيد بن طاش محمد نيازي",
		"edition": "الرياض : مكتبة العبيكات"
	},
	{
		"cat": "ق/00174",
		"ISBN": "9960319660",
		"titre": "مصطلحات علم الاجتماع",
		"autor": "سميرة أحمد السيد",
		"edition": "الرياض : مكتبة الشقري"
	},
	{
		"cat": "ق/00175",
		"ISBN": "",
		"titre": "موسوعة التاريخ العربي المعاصر والحديث",
		"autor": "مفيد الزيدي ",
		"edition": "الأردن : دار أسامة"
	},
	{
		"cat": "ق/00176",
		"ISBN": "",
		"titre": "موسوعة المستشرقين : طبعة جديدة منقحة",
		"autor": "عبد الرحمن بدوي",
		"edition": "لبنان : دار العلم للملايين"
	},
	{
		"cat": "ق/00177",
		"ISBN": "9775107970",
		"titre": "معجم مصطلحات نظم زتكنولوجيا المعلومات والاتصالات : انجليزي -عربي",
		"autor": "مفتاح محمد دياب ",
		"edition": "القاهرة : الدار الدولية "
	},
	{
		"cat": "ق/00178",
		"ISBN": "",
		"titre": "تنمية مهارات مسئولي التدريب",
		"autor": "صلاح عباس",
		"edition": "الاسكندرية : مؤسسة شباب الجامعة "
	},
	{
		"cat": "ق/00179",
		"ISBN": "",
		"titre": "موسوعة عالم المعرفة",
		"autor": "ليونارد سيلي م.إد",
		"edition": "لبنان : دار نوبليس"
	},
	{
		"cat": "ق/00180",
		"ISBN": "9960725480",
		"titre": "المعجم العربي للمواد المخدرة والعقاقير النفسية ",
		"autor": "جابر بن سالم موسى ",
		"edition": "الرياض : مكتبة الملك فهد"
	},
	{
		"cat": "ق/00181",
		"ISBN": "",
		"titre": "موسوعة فسيولوجيا مسابقات المضمار ",
		"autor": "السكار ابراهيم سالم ، زاهر عبد الرحمن عبد الحميد ، حسين احمد سالم ",
		"edition": "القاهرة : مركز الكتاب "
	},
	{
		"cat": "ق/00182",
		"ISBN": "9948852206",
		"titre": "الموسوعة العلمية لرياضة السباحة ",
		"autor": "رزق سمير عبد الله ",
		"edition": "عمان : (د.ن)"
	},
	{
		"cat": "ق/00183",
		"ISBN": "",
		"titre": "موسوعة عالم علم النفس : من 1 إلى 4 و من 6 إلى 24",
		"autor": "الحذفي عبد المنعم ",
		"edition": "بيروت : نوبليس"
	},
	{
		"cat": "ق/00184",
		"ISBN": "",
		"titre": "موسوعة علم النفس و التربية و الإجتماع : ج1-ج2-ج3-ج4-ج5-ج6-ج7-ج8-ج9-ج11-ج12-ج13-ج14",
		"autor": "عيسوي عبد الرحمن محمد ",
		"edition": "بيروت : راتب "
	},
	{
		"cat": "ق/00185",
		"ISBN": "",
		"titre": "الذاكرة الإدراك الوعي ",
		"autor": "دافيدوف لندا ",
		"edition": "القاهرة : د.د.إ"
	},
	{
		"cat": "ق/00186",
		"ISBN": "",
		"titre": "قاموس تفسير الأحلام ",
		"autor": "بوزواوي محمد ",
		"edition": "(د.م) : مدني "
	},
	{
		"cat": "ق/00187",
		"ISBN": "",
		"titre": "موسوعة التدريب الرياضي التطبيقي ",
		"autor": "حسانين محمد صبحي ",
		"edition": "القاهرة : م.ك "
	},
	{
		"cat": "ق/00188",
		"ISBN": "",
		"titre": "معجم علم النفس ",
		"autor": "عاقل فاخر ",
		"edition": "بيروت : العلم "
	},
	{
		"cat": "ق/00189",
		"ISBN": "2721422375",
		"titre": "المنجد في اللغة و الأعلام ",
		"autor": "",
		"edition": "بيروت : دار المشرق "
	},
	{
		"cat": "ق/00190",
		"ISBN": "9789947213193",
		"titre": "Dictionnaire Encyclopédique De L'algerie : culture -politique -société -histoire - personnalités - lieux -événements",
		"autor": "Cheurfi Achour",
		"edition": "Alger : ANEP"
	},
	{
		"cat": "ق/00191",
		"ISBN": "2707144495",
		"titre": "Le Dictionnaire Historique Et Géopolitique Du 20 Siécle",
		"autor": "Cordellier Serge",
		"edition": "Paris : La Découverte"
	},
	{
		"cat": "ق/00192",
		"ISBN": "2130473202",
		"titre": "Dictionnaire Historique De L'islam",
		"autor": "Janine Et Dominique Sourdel ",
		"edition": "Paris : Puf"
	},
	{
		"cat": "ق/00193",
		"ISBN": "",
		"titre": " يهود العراق ",
		"autor": "بصري مير",
		"edition": "هولندة : اكادمية الكوفة"
	},
	{
		"cat": "ق/00194",
		"ISBN": "",
		"titre": "موسوعة اشهر النساء في التاريخ القديم : منذ فجر الاسلام حتى العصر الجاهلي",
		"autor": "ديوان عبد الحميد ",
		"edition": "لبنان : دار كتابنا"
	},
	{
		"cat": "ق/00195",
		"ISBN": "",
		"titre": "موسوعة عواصم الاسلام",
		"autor": "علبي عاطف",
		"edition": "بيروت : دار مجد "
	},
	{
		"cat": "ق/00196",
		"ISBN": "5281006008497",
		"titre": "موسوعة دول العالم الاسلامي ورجالها ج1،ج2،ج3",
		"autor": "مصطفى شاكر",
		"edition": "لبنان : دار العلم للملايين"
	},
	{
		"cat": "ق/00197",
		"ISBN": "",
		"titre": "موسوعة الاديان والافكار والمنظمات القائمة عليها",
		"autor": "مهندس رها",
		"edition": "حلب : دار الحافظ للكتاب"
	},
	{
		"cat": "ق/00198",
		"ISBN": "9789953184845",
		"titre": "موسوعة الحضارات القديمة : المسيرة",
		"autor": "طقوش محمد سهيل",
		"edition": "لبنان : دار النفائس"
	},
	{
		"cat": "ق/00199",
		"ISBN": "9789957710620",
		"titre": "موسوعة علوم الارض",
		"autor": "الكيلاني عامر عبد الفتاح ",
		"edition": "عمان : دار دجلة"
	},
	{
		"cat": "ق/00200",
		"ISBN": "9789773277933",
		"titre": "الموسوعة العلمية الرياضية : المدرب الرياضي من خلال معايير الجودة الشاملة",
		"autor": "قشطة عمر نصرالله",
		"edition": "الإسكندرية : الوفاء"
	},
	{
		"cat": "ق/00201",
		"ISBN": "9789773277531",
		"titre": "الموسوعة العلمية دراسات تطبيقية في مجال التربية البدنية و الرياصية : التدريب الرياضي للملاكمين =Sports training for boxers",
		"autor": "سيف عبد الرحمن عبد العظيم",
		"edition": "الإسكندرية : الوفاء"
	},
	{
		"cat": "ق/00202",
		"ISBN": "9789773277868",
		"titre": "الموسوعة العلمية للإدارة الرياضية : تطبيقات ميدانية معاصرة في الإستثمار و التمويل في التربية البدنية و الرياضية",
		"autor": "الشافعى حسن احمد",
		"edition": "الإسكندرية : د.الوفاء"
	},
	{
		"cat": "ق/00203",
		"ISBN": "9789770318852",
		"titre": "الموسوعة العلمية و التطبيقية : الاتجاهات و المحددات الحديثة لأساليب التقنين و التخطيط للبرامج التدريبية برياضةالكاراتيه",
		"autor": "ابراهيم احمد محمد",
		"edition": "الإسكندرية : المعارف"
	},
	{
		"cat": "ق/00204",
		"ISBN": "9789773278832",
		"titre": "الموسوعة الكاملة في الإعداد البدني للنساء",
		"autor": "التكريتي وديع ياسين و اخر",
		"edition": "الإسكندرية : د.الوفاء"
	},
	{
		"cat": "ق/00205",
		"ISBN": "",
		"titre": "التغيرات البيوكيميائية للرياضيين",
		"autor": "عبد الرحمن عبد العظيم سيف",
		"edition": "الاسكندرية : الوفاء"
	},
	{
		"cat": "ق/00206",
		"ISBN": "",
		"titre": "اللياقة الفسيولوجية للملاكمين : الموسوعة العلمية دراسات تطبيقية في مجدال التربية البدنية والرياضية ",
		"autor": "عبد الرحمن عبد العظيم سيف",
		"edition": "الاسكندرية : الوفاء"
	},
	{
		"cat": "ق/00207",
		"ISBN": "9789957325015",
		"titre": "الأمم المتحدة ج1-ج2-ج3 : أهداف الأمم المتحدة -أجهزة الأمم المتحدة -الإنجازات والإخفاقات ",
		"autor": "الفتلاوي سهيل حسين ",
		"edition": "عمان : الحامد "
	},
	{
		"cat": "ق/00208",
		"ISBN": "9789957325091",
		"titre": "جامعة الدول العربية في مواجهة تحديات العولمة ج1-ج2 : إنشاء الجامعة وأهدافها -أجهزة الجامعة ",
		"autor": "الفتلاوي سهيل حسين ",
		"edition": "عمان : الحامد "
	},
	{
		"cat": "ق/00209",
		"ISBN": "9789773278796",
		"titre": "الموسوعة الإحصائية والتطبيقات الحاسوبية في بحوث التربية البدنية والرياضة ",
		"autor": "التكريتي وديع ياسين محمد ",
		"edition": "الإسكندرية : دار الوفاء "
	},
	{
		"cat": "ق/00210",
		"ISBN": "",
		"titre": "تمرينات جمل العروض الرياضية ج1 : نظريات التمرينات جمل تمرينات بالعصا (زوجية )",
		"autor": "توفيق فراج عبد الحميد ",
		"edition": "الإسكندرية : دار الوفاء "
	},
	{
		"cat": "ق/00211",
		"ISBN": "",
		"titre": "المداخل المعاصرة في إدارة الأفراد والتطوير التنظيمي في التربية البدنية الرياضية ",
		"autor": "الشافعي حسن احمد ",
		"edition": "الإسكندرية : دار الوفاء "
	},
	{
		"cat": "ق/00212",
		"ISBN": "9789772944399",
		"titre": "الكاراتيه بأحدث الطرق العلمية والعملية : رياضة متكاملة ",
		"autor": "زيدان احمد ابراهيم بكر ",
		"edition": "القاهرة : مركز الكتاب "
	},
	{
		"cat": "ق/00213",
		"ISBN": "",
		"titre": "الإدارة الإستراتيجية والتخطيط الإستراتيجي في التربية البدنية والرياضية ",
		"autor": "الشافعي حسن احمد ",
		"edition": "الإسكندرية : دار الوفاء "
	},
	{
		"cat": "ق/00214",
		"ISBN": "9782849029589",
		"titre": "Le Robert Dictionair De Français",
		"autor": "Le Robert",
		"edition": "Le Robert : Paris"
	},
	{
		"cat": "ق/00215",
		"ISBN": "9782745151346",
		"titre": "معجم الطلاب الوسيط عربي- فرنسي",
		"autor": "م. بيضون",
		"edition": "لبنان : الكتب العلمية "
	},
	{
		"cat": "ق/00216",
		"ISBN": "9782745138156",
		"titre": "معجم الطلاب الوسيط فرنسي -عربي",
		"autor": "م.بيضون",
		"edition": "لبنان : الكتب العلمية "
	},
	{
		"cat": "ق/00217",
		"ISBN": "9782745154125",
		"titre": "معجم الطالب عربي -فرنسي فرنسي- عربي",
		"autor": "م .بيضون",
		"edition": "لبنان : الكتب العلمية "
	},
	{
		"cat": "ق/00218",
		"ISBN": "",
		"titre": "بحوث في الشخصية الإدمانية : ج1 - ج2 - ج3 - ج4 - ج5 - ج6 ",
		"autor": "أبوزيد مدحت عبد الحميد ",
		"edition": "الاسكندرية : د،م،ج "
	},
	{
		"cat": "ق/00219",
		"ISBN": "9789957247669",
		"titre": "معجم المصطلحات والمفاهيم الجغرافية : الجزء الاول-الجزء الثاني",
		"autor": "محمد صالح ربيع العجيلي",
		"edition": "الاردن : صفاء"
	},
	{
		"cat": "ق/00220",
		"ISBN": "",
		"titre": "الجريمة و الإدمان ",
		"autor": "العيسوي عبد الرحمن محمد ",
		"edition": "بيروت : الراتب "
	},
	{
		"cat": "ق/00221",
		"ISBN": "9789773278818",
		"titre": "الدورات الاوليمبية والمجتمع الدولي المعاصر : الموسوعة العلمية 1",
		"autor": "حسن احمد الشافعي",
		"edition": "الاسكندرية : الوفاء"
	},
	{
		"cat": "ق/00222",
		"ISBN": "9789773279073",
		"titre": "المآذن العثمانية : المجلد الاول",
		"autor": "محمد احمد عبد اللطيف ",
		"edition": "الاسكندرية : الوفاء "
	},
	{
		"cat": "ق/00223",
		"ISBN": "",
		"titre": "التغيرات البيوكيميائية للتدريب المستمر و الفتري للملاكمين ",
		"autor": "سيف عبد الرحمن عبد العظيم ",
		"edition": "الاسكندرية : الوفاء "
	},
	{
		"cat": "ق/00224",
		"ISBN": "9773501825",
		"titre": "الجذور التاريخية للحروب الصليبية ",
		"autor": "الصلابي علي محمد محمد ",
		"edition": "القاهرة : ك،ح "
	},
	{
		"cat": "ق/00225",
		"ISBN": "9789957223113",
		"titre": "معجم الامراض وعلاجها ",
		"autor": "زينب منصور ",
		"edition": "الاردن : اسامة "
	},
	{
		"cat": "ق/00226",
		"ISBN": "9789957880064",
		"titre": "معجم مصطلحات التاريخ والحضارة الاسلامية ",
		"autor": "انور محمود زناتي ",
		"edition": "الاردن : زهران "
	},
	{
		"cat": "ق/00227",
		"ISBN": "9789957223250",
		"titre": "معجم العلوم التربوية : مزدوج",
		"autor": "ماجد محمد الشمدين ",
		"edition": "الاردن : اسامة"
	},
	{
		"cat": "ق/00228",
		"ISBN": "9789957224295",
		"titre": "المعجم الرياضي ",
		"autor": "علي حسن ابو جاموس",
		"edition": "الاردن : اسامة"
	},
	{
		"cat": "ق/00229",
		"ISBN": "",
		"titre": "معجم المصطلحات الفلسفية : فرنسي -عربي ",
		"autor": "عبده الحلو ",
		"edition": "لبنان : المركز التربوي للبحوث "
	},
	{
		"cat": "ق/00230",
		"ISBN": "9772581485",
		"titre": "موسوعة بيئة الوطن العربي : اغرب المجتمعات ",
		"autor": "احمد عبد الوهاب عبد الجواد",
		"edition": "القاهرة : الدار العربية "
	},
	{
		"cat": "ق/00231",
		"ISBN": "9772581027",
		"titre": "حتمية التحول من الزراعات الصناعية الى الزراعات العضوية في الوطن العربي",
		"autor": "احمد عبد الوهاب عبد الجواد",
		"edition": "القاهرة : الدار العربية"
	},
	{
		"cat": "ق/00232",
		"ISBN": "9772580932",
		"titre": "قضايا النفايات في الوطن العربي ",
		"autor": "احمد عبد الوهاب ",
		"edition": "القاهرة : الدار العربية "
	},
	{
		"cat": "ق/00233",
		"ISBN": "9789957327538",
		"titre": "المعجم العربي : تحديد المصطلحات النفسية",
		"autor": "علي عبد الرحيم صالح",
		"edition": "عمان : الحامد"
	},
	{
		"cat": "ق/00234",
		"ISBN": "9789770320075",
		"titre": "موسوعة تمرينات اللياقة البدنية : مهارات كرة القدم",
		"autor": "مفتي ابراهيم",
		"edition": "الاسكندرية : منشاة المعارف"
	},
	{
		"cat": "ق/00235",
		"ISBN": "9789770319819",
		"titre": "الموسوعة الرياضية الثقافية",
		"autor": "ناجي الباجوري",
		"edition": "الاسكندرية : المعارف"
	},
	{
		"cat": "ق/00236",
		"ISBN": "9789957831950",
		"titre": "الموسوعة العالمية لكرة القدم : الجزء1-2-3-4",
		"autor": "غازي صالح محمود",
		"edition": "الاردن : م م ع "
	},
	{
		"cat": "ق/00237",
		"ISBN": "272947669",
		"titre": "DICTIONNAIRE ENCYCLOPEDIQUE DES SCIENCES DE L'INFORMATIOM ET DE LA COMMUNICATION",
		"autor": "LAMIZET BENARD",
		"edition": "PARIS : ELLIPSES"
	},
	{
		"cat": "ق/00238",
		"ISBN": "2200014279",
		"titre": "DICTIONNAIRE DES METHODES QUALITATIVES EN SCIENCES HUMAINES ET SOCIALES",
		"autor": "ALEX MUCCHIELLI",
		"edition": "PARIS : ARMAND COLIN "
	},
	{
		"cat": "ق/00239",
		"ISBN": "2851806602",
		"titre": "Encyclopédie technique historique biographique et culturelle : Des arts materiaux de l'extreme-Orient",
		"autor": "Habersetzer Gabrielle",
		"edition": "Paris : amphora"
	},
	{
		"cat": "ق/00240",
		"ISBN": "2130459110",
		"titre": "Dictionnaire critique de la sociologie",
		"autor": "Boudon Raymond",
		"edition": "Paris : puf"
	},
	{
		"cat": "ق/00241",
		"ISBN": "",
		"titre": "A Dictionnaire of the social sciences : English-french-arabic",
		"autor": "Badawi Zaki",
		"edition": "Beirut : Librairie du Liban"
	},
	{
		"cat": "ق/00242",
		"ISBN": "2091905267",
		"titre": "DICTIONNAIRE DES SCIENCES HUMAINES : SOCILOGIE/ANTHROPOLOGIE",
		"autor": "GRSLE FRANCOIS",
		"edition": "PARIS : NATHAN"
	},
	{
		"cat": "ق/00243",
		"ISBN": "140513809",
		"titre": "DICTIONARY OF SOCIOLOGY ",
		"autor": "NICHOLAS ABECROMBIE",
		"edition": "ENGLAND : PENGIN REFERENCE"
	},
	{
		"cat": "ق/00244",
		"ISBN": "2037203438",
		"titre": "DICTIONNAIRE DE SOCIOLOGIE ",
		"autor": "RAYMOND BOUDON ",
		"edition": "PARIS : LAROUSSE "
	},
	{
		"cat": "ق/00245",
		"ISBN": "2091845418",
		"titre": "Dictionnaire de philosophie",
		"autor": "Durozoi Gerard",
		"edition": "paris : Nathan"
	}
]